[
  {
    "position": 1,
    "artist": "Taylor Swift",
    "track": "I Knew It, I Knew You",
    "streams": 497533
  },
  {
    "position": 2,
    "artist": "Ella Langley",
    "track": "Choosin' Texas",
    "streams": 26231582
  },
  {
    "position": 3,
    "artist": "Olivia Dean",
    "track": "Man I Need",
    "streams": 93668579
  },
  {
    "position": 4,
    "artist": "Michael Jackson",
    "track": "Billie Jean",
    "streams": 21122430
  },
  {
    "position": 5,
    "artist": "Sam Fender",
    "track": "Rein Me In (w/ Olivia Dean )",
    "streams": 36689265
  },
  {
    "position": 6,
    "artist": "Ariana Grande",
    "track": "hate that i made you love me",
    "streams": 1728272
  },
  {
    "position": 7,
    "artist": "White Noise Radiance",
    "track": "Rain Sounds for Sleeping, Pt. 06 (Continuous No Gaps) (w/ Rain Sounds )",
    "streams": 16969346
  },
  {
    "position": 8,
    "artist": "Michael Jackson",
    "track": "Beat It",
    "streams": 6239884
  },
  {
    "position": 9,
    "artist": "Drake",
    "track": "Janice STFU",
    "streams": 4361742
  },
  {
    "position": 10,
    "artist": "Olivia Rodrigo",
    "track": "the cure",
    "streams": 3251227
  },
  {
    "position": 11,
    "artist": "Malcolm Todd",
    "track": "Earrings",
    "streams": 8515427
  },
  {
    "position": 12,
    "artist": "Bella Kay",
    "track": "iloveitiloveitiloveit",
    "streams": 24831416
  },
  {
    "position": 13,
    "artist": "Dominic Fike",
    "track": "Babydoll",
    "streams": 49583417
  },
  {
    "position": 14,
    "artist": "The Killers",
    "track": "Mr. Brightside",
    "streams": 237616216
  },
  {
    "position": 15,
    "artist": "Justin Bieber",
    "track": "Beauty And A Beat (w/ Nicki Minaj )",
    "streams": 12990694
  },
  {
    "position": 16,
    "artist": "sombr",
    "track": "Homewrecker",
    "streams": 19191713
  },
  {
    "position": 17,
    "artist": "Olivia Dean",
    "track": "So Easy (To Fall In Love)",
    "streams": 50617037
  },
  {
    "position": 18,
    "artist": "Michael Jackson",
    "track": "Human Nature",
    "streams": 5165689
  },
  {
    "position": 19,
    "artist": "Michael Jackson",
    "track": "Chicago",
    "streams": 3679820
  },
  {
    "position": 20,
    "artist": "Zara Larsson",
    "track": "Lush Life",
    "streams": 51668516
  },
  {
    "position": 21,
    "artist": "Justin Bieber",
    "track": "DAISIES",
    "streams": 51530950
  },
  {
    "position": 22,
    "artist": "sombr",
    "track": "12 to 12",
    "streams": 54026284
  },
  {
    "position": 23,
    "artist": "Michael Jackson",
    "track": "Don't Stop 'Til You Get Enough - Single Version",
    "streams": 4926375
  },
  {
    "position": 24,
    "artist": "Disco Lines",
    "track": "No Broke Boys (w/ Tinashe )",
    "streams": 70159589
  },
  {
    "position": 25,
    "artist": "The Goo Goo Dolls",
    "track": "Iris",
    "streams": 142343270
  },
  {
    "position": 26,
    "artist": "Fleetwood Mac",
    "track": "Dreams - 2001 Remaster",
    "streams": 6251486
  },
  {
    "position": 27,
    "artist": "RAYE",
    "track": "WHERE IS MY HUSBAND!",
    "streams": 44470889
  },
  {
    "position": 28,
    "artist": "Dave",
    "track": "Raindance (w/ Tems )",
    "streams": 30003735
  },
  {
    "position": 29,
    "artist": "Mac Miller",
    "track": "Cinderella (w/ Ty Dolla $ign )",
    "streams": 2471022
  },
  {
    "position": 30,
    "artist": "Benson Boone",
    "track": "Beautiful Things",
    "streams": 151826902
  },
  {
    "position": 31,
    "artist": "Dominic Fike",
    "track": "White Keys",
    "streams": 15748234
  },
  {
    "position": 32,
    "artist": "Olivia Rodrigo",
    "track": "drop dead",
    "streams": 8168750
  },
  {
    "position": 33,
    "artist": "PinkPantheress",
    "track": "Stateside + Zara Larsson (w/ Zara Larsson )",
    "streams": 23745948
  },
  {
    "position": 34,
    "artist": "F3miii",
    "track": "NOBLE",
    "streams": 4649530
  },
  {
    "position": 35,
    "artist": "Djo",
    "track": "End of Beginning",
    "streams": 86904551
  },
  {
    "position": 36,
    "artist": "sombr",
    "track": "back to friends",
    "streams": 74151498
  },
  {
    "position": 37,
    "artist": "Temper City",
    "track": "Self Aware",
    "streams": 4480379
  },
  {
    "position": 38,
    "artist": "Ravyn Lenae",
    "track": "Love Me Not",
    "streams": 56997920
  },
  {
    "position": 39,
    "artist": "Alex Warren",
    "track": "Ordinary",
    "streams": 97770143
  },
  {
    "position": 40,
    "artist": "Taylor Swift",
    "track": "The Fate of Ophelia",
    "streams": 52892644
  },
  {
    "position": 41,
    "artist": "HUNTR/X",
    "track": "Golden (w/ EJae , AUDREY NUNA , REI AMI , KPop Demon Hunters Cast )",
    "streams": 72920582
  },
  {
    "position": 42,
    "artist": "Olivia Dean",
    "track": "Nice To Each Other",
    "streams": 50756396
  },
  {
    "position": 43,
    "artist": "Kings of Leon",
    "track": "Sex on Fire",
    "streams": 111521336
  },
  {
    "position": 44,
    "artist": "Ella Langley",
    "track": "Be Her",
    "streams": 5353529
  },
  {
    "position": 45,
    "artist": "Michael Jackson",
    "track": "Dirty Diana - 2012 Remaster",
    "streams": 3726557
  },
  {
    "position": 46,
    "artist": "G Flip",
    "track": "Bed on Fire",
    "streams": 1273017
  },
  {
    "position": 47,
    "artist": "Michael Jackson",
    "track": "Smooth Criminal - 2012 Remaster",
    "streams": 3537236
  },
  {
    "position": 48,
    "artist": "STELLA LEFTY",
    "track": "Boston",
    "streams": 5265990
  },
  {
    "position": 49,
    "artist": "Drake",
    "track": "National Treasures",
    "streams": 3356020
  },
  {
    "position": 50,
    "artist": "The Chemical Brothers",
    "track": "Go",
    "streams": 3633138
  },
  {
    "position": 51,
    "artist": "Natasha Bedingfield",
    "track": "Unwritten",
    "streams": 60004564
  },
  {
    "position": 52,
    "artist": "Tame Impala",
    "track": "Dracula - JENNIE Remix (w/ JENNIE )",
    "streams": 9267383
  },
  {
    "position": 53,
    "artist": "Shaboozey",
    "track": "A Bar Song (Tipsy)",
    "streams": 131653997
  },
  {
    "position": 54,
    "artist": "Hozier",
    "track": "Too Sweet",
    "streams": 98848361
  },
  {
    "position": 55,
    "artist": "Zach Bryan",
    "track": "I Remember Everything (w/ Kacey Musgraves )",
    "streams": 123467664
  },
  {
    "position": 56,
    "artist": "Jennifer Lopez",
    "track": "On The Floor (w/ Pitbull )",
    "streams": 1232503
  },
  {
    "position": 57,
    "artist": "Alyssa Grace",
    "track": "bloodstream",
    "streams": 168166
  },
  {
    "position": 58,
    "artist": "Alex Warren",
    "track": "FEVER DREAM",
    "streams": 9859400
  },
  {
    "position": 59,
    "artist": "Teddy Swims",
    "track": "Lose Control",
    "streams": 131295471
  },
  {
    "position": 60,
    "artist": "Katy Perry",
    "track": "The One That Got Away",
    "streams": 3636128
  },
  {
    "position": 61,
    "artist": "Tame Impala",
    "track": "Dracula",
    "streams": 21809987
  },
  {
    "position": 62,
    "artist": "Michael Jackson",
    "track": "Bad - 2012 Remaster",
    "streams": 2588885
  },
  {
    "position": 63,
    "artist": "sombr",
    "track": "undressed",
    "streams": 65927011
  },
  {
    "position": 64,
    "artist": "Zara Larsson",
    "track": "Midnight Sun",
    "streams": 10162673
  },
  {
    "position": 65,
    "artist": "Drake",
    "track": "Shabang",
    "streams": 2546180
  },
  {
    "position": 66,
    "artist": "Gracie Abrams",
    "track": "Hit the Wall",
    "streams": 2243549
  },
  {
    "position": 67,
    "artist": "TLC",
    "track": "No Scrubs",
    "streams": 62060716
  },
  {
    "position": 68,
    "artist": "Myles Smith",
    "track": "Stargazing",
    "streams": 74327730
  },
  {
    "position": 69,
    "artist": "Harry Styles",
    "track": "American Girls",
    "streams": 11635102
  },
  {
    "position": 70,
    "artist": "Fleetwood Mac",
    "track": "Everywhere",
    "streams": 3682102
  },
  {
    "position": 71,
    "artist": "Don Toliver",
    "track": "E85",
    "streams": 9540301
  },
  {
    "position": 72,
    "artist": "Billie Eilish",
    "track": "BIRDS OF A FEATHER",
    "streams": 135437976
  },
  {
    "position": 73,
    "artist": "TOTO",
    "track": "Africa",
    "streams": 106487893
  },
  {
    "position": 74,
    "artist": "Coldplay",
    "track": "Viva La Vida",
    "streams": 76292654
  },
  {
    "position": 75,
    "artist": "Michael Jackson",
    "track": "Thriller",
    "streams": 3180728
  },
  {
    "position": 76,
    "artist": "Dexter and The Moonrocks",
    "track": "Freakin’ Out",
    "streams": 4567052
  },
  {
    "position": 77,
    "artist": "Zach Bryan",
    "track": "Pink Skies",
    "streams": 67794082
  },
  {
    "position": 78,
    "artist": "ROSÉ",
    "track": "APT. (w/ Bruno Mars )",
    "streams": 81869806
  },
  {
    "position": 79,
    "artist": "Post Malone",
    "track": "I Had Some Help (Feat. Morgan Wallen) (w/ Morgan Wallen )",
    "streams": 111513833
  },
  {
    "position": 80,
    "artist": "Drake",
    "track": "One Dance (w/ Wizkid , Kyla )",
    "streams": 130020387
  },
  {
    "position": 81,
    "artist": "Gorillaz",
    "track": "Feel Good Inc",
    "streams": 42815697
  },
  {
    "position": 82,
    "artist": "Red Hot Chili Peppers",
    "track": "Scar Tissue - 2014 Remaster",
    "streams": 6839150
  },
  {
    "position": 83,
    "artist": "Fleetwood Mac",
    "track": "Landslide",
    "streams": 21233762
  },
  {
    "position": 84,
    "artist": "Michael Jackson",
    "track": "The Way You Make Me Feel - 2012 Remaster",
    "streams": 2913969
  },
  {
    "position": 85,
    "artist": "The Neighbourhood",
    "track": "Sweater Weather",
    "streams": 124122153
  },
  {
    "position": 86,
    "artist": "Vance Joy",
    "track": "Riptide",
    "streams": 217456939
  },
  {
    "position": 87,
    "artist": "Noah Kahan",
    "track": "Stick Season",
    "streams": 123129668
  },
  {
    "position": 88,
    "artist": "Macklemore & Ryan Lewis",
    "track": "Can't Hold Us (w/ Macklemore , Ryan Lewis , Ray Dalton )",
    "streams": 83988807
  },
  {
    "position": 89,
    "artist": "Red Hot Chili Peppers",
    "track": "Under the Bridge",
    "streams": 53971950
  },
  {
    "position": 90,
    "artist": "Creedence Clearwater Revival",
    "track": "Have You Ever Seen The Rain",
    "streams": 77410351
  },
  {
    "position": 91,
    "artist": "Olivia Dean",
    "track": "Ok Love You Bye",
    "streams": 20858369
  },
  {
    "position": 92,
    "artist": "Fleetwood Mac",
    "track": "The Chain - 2001 Remaster",
    "streams": 3629357
  },
  {
    "position": 93,
    "artist": "Olivia Dean",
    "track": "The Hardest Part",
    "streams": 25353594
  },
  {
    "position": 94,
    "artist": "Gigi Perez",
    "track": "Sailor Song",
    "streams": 77879766
  },
  {
    "position": 95,
    "artist": "Bruno Mars",
    "track": "I Just Might",
    "streams": 17067620
  },
  {
    "position": 96,
    "artist": "Train",
    "track": "Drops of Jupiter",
    "streams": 40259062
  },
  {
    "position": 97,
    "artist": "Kings of Leon",
    "track": "Use Somebody",
    "streams": 32460143
  },
  {
    "position": 98,
    "artist": "Chrystal",
    "track": "The Days - NOTION Remix (w/ NOTION )",
    "streams": 59708282
  },
  {
    "position": 99,
    "artist": "Wheatus",
    "track": "Teenage Dirtbag",
    "streams": 20341516
  },
  {
    "position": 100,
    "artist": "Coldplay",
    "track": "Yellow",
    "streams": 106766919
  },
  {
    "position": 101,
    "artist": "Zach Bryan",
    "track": "Something in the Orange",
    "streams": 150862131
  },
  {
    "position": 102,
    "artist": "Nelly Furtado",
    "track": "Promiscuous (w/ Timbaland )",
    "streams": 73310920
  },
  {
    "position": 103,
    "artist": "Taylor Swift",
    "track": "Opalite",
    "streams": 34507470
  },
  {
    "position": 104,
    "artist": "Chappell Roan",
    "track": "Pink Pony Club",
    "streams": 70428861
  },
  {
    "position": 105,
    "artist": "Harry Styles",
    "track": "Sign of the Times",
    "streams": 17821130
  },
  {
    "position": 106,
    "artist": "Michael Jackson",
    "track": "Man in the Mirror - 2012 Remaster",
    "streams": 2540347
  },
  {
    "position": 107,
    "artist": "The Police",
    "track": "Every Breath You Take",
    "streams": 52551467
  },
  {
    "position": 108,
    "artist": "Michael Jackson",
    "track": "Rock with You - Single Version",
    "streams": 2703846
  },
  {
    "position": 109,
    "artist": "Michael Jackson",
    "track": "P.Y.T. (Pretty Young Thing)",
    "streams": 2381112
  },
  {
    "position": 110,
    "artist": "Bruce Springsteen",
    "track": "I'm on Fire",
    "streams": 14673117
  },
  {
    "position": 111,
    "artist": "Nickelback",
    "track": "How You Remind Me",
    "streams": 46641321
  },
  {
    "position": 112,
    "artist": "Men At Work",
    "track": "Down Under",
    "streams": 24947781
  },
  {
    "position": 113,
    "artist": "Michael Jackson",
    "track": "They Don't Care About Us",
    "streams": 2736425
  },
  {
    "position": 114,
    "artist": "Crowded House",
    "track": "Don't Dream It's Over",
    "streams": 47711682
  },
  {
    "position": 115,
    "artist": "Ella Langley",
    "track": "weren't for the wind",
    "streams": 12163087
  },
  {
    "position": 116,
    "artist": "The Jackson 5",
    "track": "I Want You Back",
    "streams": 2239292
  },
  {
    "position": 117,
    "artist": "The Beaches",
    "track": "Edge of the Earth",
    "streams": 590485
  },
  {
    "position": 118,
    "artist": "Harry Styles",
    "track": "As It Was",
    "streams": 134288528
  },
  {
    "position": 119,
    "artist": "Linkin Park",
    "track": "In the End",
    "streams": 37797577
  },
  {
    "position": 120,
    "artist": "Chris Stapleton",
    "track": "Tennessee Whiskey",
    "streams": 61713464
  },
  {
    "position": 121,
    "artist": "Gracie Abrams",
    "track": "That’s So True",
    "streams": 90042933
  },
  {
    "position": 122,
    "artist": "Alex Warren",
    "track": "Carry You Home",
    "streams": 47400612
  },
  {
    "position": 123,
    "artist": "Elton John",
    "track": "The Bitch Is Back - Remastered 1995",
    "streams": 825855
  },
  {
    "position": 124,
    "artist": "Olivia Dean",
    "track": "Dive",
    "streams": 23664179
  },
  {
    "position": 125,
    "artist": "Tate McRae",
    "track": "Just Keep Watching (From F1® The Movie) (w/ F1 The Album )",
    "streams": 35984037
  },
  {
    "position": 126,
    "artist": "Luke Combs",
    "track": "When It Rains It Pours",
    "streams": 79485326
  },
  {
    "position": 127,
    "artist": "SIENNA SPIRO",
    "track": "Material Lover",
    "streams": 1954331
  },
  {
    "position": 128,
    "artist": "Luke Combs",
    "track": "Fast Car",
    "streams": 91754689
  },
  {
    "position": 129,
    "artist": "Hozier",
    "track": "Take Me To Church",
    "streams": 121099989
  },
  {
    "position": 130,
    "artist": "Drake",
    "track": "Whisper My Name",
    "streams": 2614619
  },
  {
    "position": 131,
    "artist": "Olivia Dean",
    "track": "Baby Steps",
    "streams": 23180276
  },
  {
    "position": 132,
    "artist": "Mac Miller",
    "track": "The Spins (w/ Empire Of The Sun )",
    "streams": 4426242
  },
  {
    "position": 133,
    "artist": "Red Hot Chili Peppers",
    "track": "Can't Stop - 2014 Remaster",
    "streams": 6308576
  },
  {
    "position": 134,
    "artist": "Chris Stapleton",
    "track": "You Should Probably Leave",
    "streams": 65234872
  },
  {
    "position": 135,
    "artist": "Noah Kahan",
    "track": "Orbiter",
    "streams": 1762338
  },
  {
    "position": 136,
    "artist": "Empire Of The Sun",
    "track": "Walking On A Dream",
    "streams": 67479085
  },
  {
    "position": 137,
    "artist": "Nirvana",
    "track": "Smells Like Teen Spirit - Remastered",
    "streams": 47136127
  },
  {
    "position": 138,
    "artist": "Sabrina Carpenter",
    "track": "Manchild",
    "streams": 39909835
  },
  {
    "position": 139,
    "artist": "Justin Bieber",
    "track": "YUKON",
    "streams": 22069340
  },
  {
    "position": 140,
    "artist": "Dire Straits",
    "track": "Sultans Of Swing",
    "streams": 26303217
  },
  {
    "position": 141,
    "artist": "Dasha",
    "track": "Austin",
    "streams": 82629906
  },
  {
    "position": 142,
    "artist": "Bruno Mars",
    "track": "Locked out of Heaven",
    "streams": 29769195
  },
  {
    "position": 143,
    "artist": "Bruno Mars",
    "track": "Risk It All",
    "streams": 9296479
  },
  {
    "position": 144,
    "artist": "Olivia Dean",
    "track": "A Couple Minutes",
    "streams": 21788677
  },
  {
    "position": 145,
    "artist": "Whiskey Myers",
    "track": "Broken Window Serenade",
    "streams": 2282975
  },
  {
    "position": 146,
    "artist": "Morgan Wallen",
    "track": "Last Night",
    "streams": 129616623
  },
  {
    "position": 147,
    "artist": "KATSEYE",
    "track": "PINKY UP",
    "streams": 3735046
  },
  {
    "position": 148,
    "artist": "The Temper Trap",
    "track": "Sweet Disposition",
    "streams": 38832338
  },
  {
    "position": 149,
    "artist": "Journey",
    "track": "Don't Stop Believin' (2022 Remaster)",
    "streams": 52982852
  },
  {
    "position": 150,
    "artist": "Bruce Springsteen",
    "track": "Dancing In the Dark",
    "streams": 35593155
  },
  {
    "position": 151,
    "artist": "SIENNA SPIRO",
    "track": "Die On This Hill",
    "streams": 14476639
  },
  {
    "position": 152,
    "artist": "The Kid LAROI",
    "track": "GIRLS",
    "streams": 20788043
  },
  {
    "position": 153,
    "artist": "Fleetwood Mac",
    "track": "Go Your Own Way - 2001 Remaster",
    "streams": 1897667
  },
  {
    "position": 154,
    "artist": "Luke Combs",
    "track": "Ain't No Love In Oklahoma (From Twisters: The Album)",
    "streams": 54401596
  },
  {
    "position": 155,
    "artist": "Outkast",
    "track": "Hey Ya!",
    "streams": 19425673
  },
  {
    "position": 156,
    "artist": "Pitbull",
    "track": "Give Me Everything (w/ Ne-Yo , AFROJACK , Nayer )",
    "streams": 21350903
  },
  {
    "position": 157,
    "artist": "Shakira",
    "track": "Hips Don't Lie (w/ Wyclef Jean )",
    "streams": 732732
  },
  {
    "position": 158,
    "artist": "Rihanna",
    "track": "Don't Stop The Music",
    "streams": 12846688
  },
  {
    "position": 159,
    "artist": "HAVEN.",
    "track": "I Run (w/ Kaitlin Aragon )",
    "streams": 17659154
  },
  {
    "position": 160,
    "artist": "Sean Paul",
    "track": "(When You Gonna) Give It Up to Me (w/ Keyshia Cole )",
    "streams": 6465357
  },
  {
    "position": 161,
    "artist": "DaBaby",
    "track": "POP DAT THANG",
    "streams": 4412379
  },
  {
    "position": 162,
    "artist": "Lady Gaga",
    "track": "Die With A Smile (w/ Bruno Mars )",
    "streams": 94398806
  },
  {
    "position": 163,
    "artist": "Radiohead",
    "track": "Creep",
    "streams": 25497854
  },
  {
    "position": 164,
    "artist": "Kendrick Lamar",
    "track": "All The Stars (w/ SZA )",
    "streams": 121535567
  },
  {
    "position": 165,
    "artist": "Mark Ronson",
    "track": "Valerie (w/ Amy Winehouse )",
    "streams": 15493017
  },
  {
    "position": 166,
    "artist": "Metallica",
    "track": "Enter Sandman - Remastered 2021",
    "streams": 26950490
  },
  {
    "position": 167,
    "artist": "Pitbull",
    "track": "Time of Our Lives (w/ Ne-Yo )",
    "streams": 27239038
  },
  {
    "position": 168,
    "artist": "Black Eyed Peas",
    "track": "Meet Me Halfway",
    "streams": 6394459
  },
  {
    "position": 169,
    "artist": "AC/DC",
    "track": "Thunderstruck",
    "streams": 30034842
  },
  {
    "position": 170,
    "artist": "Mazzy Star",
    "track": "Fade Into You",
    "streams": 14075072
  },
  {
    "position": 171,
    "artist": "French Montana",
    "track": "Unforgettable (w/ Swae Lee )",
    "streams": 62744087
  },
  {
    "position": 172,
    "artist": "Sabrina Carpenter",
    "track": "Espresso",
    "streams": 119921372
  },
  {
    "position": 173,
    "artist": "Tame Impala",
    "track": "The Less I Know The Better",
    "streams": 74495408
  },
  {
    "position": 174,
    "artist": "AC/DC",
    "track": "You Shook Me All Night Long",
    "streams": 54831396
  },
  {
    "position": 175,
    "artist": "Foo Fighters",
    "track": "Everlong",
    "streams": 37796590
  },
  {
    "position": 176,
    "artist": "WALK THE MOON",
    "track": "Shut Up and Dance",
    "streams": 71504922
  },
  {
    "position": 177,
    "artist": "Teddy Swims",
    "track": "The Door",
    "streams": 48712685
  },
  {
    "position": 178,
    "artist": "Guns N' Roses",
    "track": "Sweet Child O' Mine",
    "streams": 9061481
  },
  {
    "position": 179,
    "artist": "Clean Bandit",
    "track": "Rather Be (w/ Jess Glynne )",
    "streams": 8965233
  },
  {
    "position": 180,
    "artist": "Bruno Mars",
    "track": "Just the Way You Are",
    "streams": 47930616
  },
  {
    "position": 181,
    "artist": "Tracy Chapman",
    "track": "Fast Car",
    "streams": 12875643
  },
  {
    "position": 182,
    "artist": "Bruno Mars",
    "track": "That's What I Like",
    "streams": 42190594
  },
  {
    "position": 183,
    "artist": "Outkast",
    "track": "Ms. Jackson",
    "streams": 4291087
  },
  {
    "position": 184,
    "artist": "Oasis",
    "track": "Wonderwall - Remastered",
    "streams": 81362257
  },
  {
    "position": 185,
    "artist": "Fred again..",
    "track": "Victory Lap (w/ Skepta , PlaqueBoyMax )",
    "streams": 35447889
  },
  {
    "position": 186,
    "artist": "Noah Kahan",
    "track": "Doors",
    "streams": 3966960
  },
  {
    "position": 187,
    "artist": "Red Hot Chili Peppers",
    "track": "Californication - 2014 Remaster",
    "streams": 3576154
  },
  {
    "position": 188,
    "artist": "Rihanna",
    "track": "Only Girl (In The World)",
    "streams": 8200905
  },
  {
    "position": 189,
    "artist": "Linkin Park",
    "track": "Numb",
    "streams": 28038981
  },
  {
    "position": 190,
    "artist": "Noah Kahan",
    "track": "The Great Divide",
    "streams": 9770630
  },
  {
    "position": 191,
    "artist": "OneRepublic",
    "track": "Counting Stars",
    "streams": 91003710
  },
  {
    "position": 192,
    "artist": "Timbaland",
    "track": "The Way I Are (w/ Keri Hilson , D.O.E. )",
    "streams": 43263757
  },
  {
    "position": 193,
    "artist": "Foster The People",
    "track": "Pumped Up Kicks",
    "streams": 47930797
  },
  {
    "position": 194,
    "artist": "Chappell Roan",
    "track": "Good Luck, Babe!",
    "streams": 99833991
  },
  {
    "position": 195,
    "artist": "Cameron Whitcomb",
    "track": "Kingdom of Fear",
    "streams": 301114
  },
  {
    "position": 196,
    "artist": "Justin Bieber",
    "track": "Confident - Single Version (w/ Chance the Rapper )",
    "streams": 4370509
  },
  {
    "position": 197,
    "artist": "Bryan Adams",
    "track": "Summer Of '69",
    "streams": 79432283
  },
  {
    "position": 198,
    "artist": "AC/DC",
    "track": "Highway to Hell",
    "streams": 13935843
  },
  {
    "position": 199,
    "artist": "The Verve",
    "track": "Bitter Sweet Symphony",
    "streams": 11078252
  },
  {
    "position": 200,
    "artist": "Rihanna",
    "track": "S&M",
    "streams": 3223201
  }
]